metafold/__init__.py
metafold/api.py
metafold/assets.py
metafold/auth.py
metafold/client.py
metafold/exceptions.py
metafold/func.py
metafold/func_types.py
metafold/jobs.py
metafold/nx.py
metafold/projects.py
metafold/utils.py
metafold/workflows.py
metafold-0.11.0.dist-info/licenses/LICENSE
metafold-0.11.0.dist-info/METADATA
metafold-0.11.0.dist-info/WHEEL
metafold-0.11.0.dist-info/top_level.txt
metafold-0.11.0.dist-info/RECORD
