Metadata-Version: 2.4
Name: metafold
Version: 0.11.0
Summary: Metafold SDK for Python
Author-email: Metafold 3D <info@metafold3d.com>
License: Copyright 2024 Metafold 3D
Project-URL: Homepage, https://www.metafold3d.com/
Project-URL: Documentation, https://metafold3d.github.io/metafold-python/
Project-URL: Repository, https://github.com/Metafold3d/metafold-python.git
Project-URL: Issues, https://github.com/Metafold3d/metafold-python/issues
Keywords: metafold,api,sdk,implicit geometry
Classifier: Development Status :: 3 - Alpha
Classifier: Intended Audience :: Developers
Classifier: Intended Audience :: Science/Research
Classifier: License :: OSI Approved :: MIT License
Classifier: Operating System :: OS Independent
Classifier: Programming Language :: Python :: 3.9
Classifier: Programming Language :: Python :: 3.10
Classifier: Programming Language :: Python :: 3.11
Classifier: Programming Language :: Python :: 3.12
Classifier: Topic :: Scientific/Engineering
Classifier: Topic :: Software Development :: Libraries :: Python Modules
Requires-Python: >=3.9
License-File: LICENSE
Requires-Dist: attrs~=23.2
Requires-Dist: auth0-python~=4.7
Requires-Dist: numpy~=2.0
Requires-Dist: requests~=2.31
Requires-Dist: scipy~=1.11
Provides-Extra: docs
Requires-Dist: sphinx~=7.2; extra == "docs"
Requires-Dist: sphinx_rtd_theme~=2.0; extra == "docs"
Provides-Extra: lint
Requires-Dist: mypy~=1.10; extra == "lint"
Requires-Dist: types-requests~=2.31; extra == "lint"
Provides-Extra: test
Requires-Dist: pytest~=7.3; extra == "test"
Requires-Dist: requests-toolbelt~=1.0; extra == "test"
Provides-Extra: networkx
Requires-Dist: networkx~=3.2; extra == "networkx"
Requires-Dist: types-networkx~=3.2; extra == "networkx"
Dynamic: license-file
